uncharted/__init__.py
uncharted/criteria.py
uncharted/explorer.py
uncharted/parameters.py
uncharted/samplers/__init__.py
uncharted/samplers/grid.py
uncharted/samplers/random.py
uncharted/samplers/sampler.py
uncharted-0.1.0.dist-info/METADATA
uncharted-0.1.0.dist-info/WHEEL
uncharted-0.1.0.dist-info/licenses/LICENSE
uncharted-0.1.0.dist-info/RECORD
