Metadata-Version: 2.3
Name: uncharted
Version: 0.1.0
Summary: Black box explorer
Author-email: Alan Sanders <asanders@users.noreply.github.com>
License: MIT License
License-File: LICENSE
Requires-Python: >=3.10
Requires-Dist: loguru>=0.7.2
Requires-Dist: numpy>=2.1.1
Requires-Dist: scipy>=1.14.0
Provides-Extra: examples
Requires-Dist: ipykernel>=6.29.5; extra == 'examples'
Requires-Dist: matplotlib>=3.9.2; extra == 'examples'
Requires-Dist: tqdm>=4.66.5; extra == 'examples'
